bench/__init__.py
bench/app.py
bench/bench.py
bench/cli.py
bench/exceptions.py
bench/commands/__init__.py
bench/commands/config.py
bench/commands/git.py
bench/commands/install.py
bench/commands/make.py
bench/commands/setup.py
bench/commands/update.py
bench/commands/utils.py
bench/config/__init__.py
bench/config/common_site_config.py
bench/config/lets_encrypt.py
bench/config/nginx.py
bench/config/procfile.py
bench/config/production_setup.py
bench/config/redis.py
bench/config/site_config.py
bench/config/supervisor.py
bench/config/systemd.py
bench/config/templates/502.html
bench/config/templates/Procfile
bench/config/templates/bench_manager_nginx.conf
bench/config/templates/harpiya_sudoers
bench/config/templates/letsencrypt.cfg
bench/config/templates/nginx.conf
bench/config/templates/nginx_default.conf
bench/config/templates/redis_cache.conf
bench/config/templates/redis_queue.conf
bench/config/templates/redis_socketio.conf
bench/config/templates/supervisor.conf
bench/config/templates/systemd/harpiya-bench-harpiya-default-worker.service
bench/config/templates/systemd/harpiya-bench-harpiya-long-worker.service
bench/config/templates/systemd/harpiya-bench-harpiya-schedule.service
bench/config/templates/systemd/harpiya-bench-harpiya-short-worker.service
bench/config/templates/systemd/harpiya-bench-harpiya-web.service
bench/config/templates/systemd/harpiya-bench-node-socketio.service
bench/config/templates/systemd/harpiya-bench-redis-cache.service
bench/config/templates/systemd/harpiya-bench-redis-queue.service
bench/config/templates/systemd/harpiya-bench-redis-socketio.service
bench/config/templates/systemd/harpiya-bench-redis.target
bench/config/templates/systemd/harpiya-bench-web.target
bench/config/templates/systemd/harpiya-bench-workers.target
bench/config/templates/systemd/harpiya-bench.target
bench/patches/__init__.py
bench/patches/patches.txt
bench/patches/v5/__init__.py
bench/patches/v5/fix_backup_cronjob.py
bench/patches/v5/fix_user_permissions.py
harpiya_bench-5.2.0.dist-info/METADATA
harpiya_bench-5.2.0.dist-info/WHEEL
harpiya_bench-5.2.0.dist-info/entry_points.txt
harpiya_bench-5.2.0.dist-info/licenses/LICENSE
harpiya_bench-5.2.0.dist-info/RECORD
