Metadata-Version: 2.1
Name: harpiya-bench
Version: 5.2.0
Summary: CLI to manage Multi-tenant deployments for Harpiyaapps
Project-URL: Changelog, https://github.com/harpiyacloud/bench/releases
Project-URL: Documentation, https://harpiya.cloud/docs/user/en/bench
Project-URL: Homepage, https://harpiya.cloud/bench
Project-URL: Source, https://github.com/harpiyacloud/bench
Author-email: Harpiya Software Technologies <developers@harpiya.com>
Classifier: Development Status :: 5 - Production/Stable
Classifier: Environment :: Console
Classifier: License :: OSI Approved :: GNU Affero General Public License v3
Classifier: Natural Language :: English
Classifier: Operating System :: MacOS
Classifier: Operating System :: OS Independent
Classifier: Topic :: Software Development :: Build Tools
Classifier: Topic :: Software Development :: User Interfaces
Classifier: Topic :: System :: Installation/Setup
Requires-Python: >=3.7
Requires-Dist: click>=7.0
Requires-Dist: gitpython~=2.1.15
Requires-Dist: honcho
Requires-Dist: jinja2~=3.0.3
Requires-Dist: python-crontab~=2.6.0
Requires-Dist: requests
Requires-Dist: semantic-version~=2.8.2
Requires-Dist: setuptools>40.9.0
Requires-Dist: tomli; python_version < '3.11'
